{"apps":[{"id":1776926983562,"date":"2026-04-23","platform":"LinkedIn Dubai","region":"dubai","title":"Account manager local shops","company":"Talabat","url":"https://www.linkedin.com/jobs/view/4368564945/","type":"Easy Apply","status":"Applied","notes":"","stages":[]},{"id":1776891343978,"date":"2026-04-22","platform":"Indeed Netherlands","region":"nl","title":"Juridisch medewerker franchise","company":"Actief werkt","url":"","type":"Easy Apply","status":"Interview","notes":"‼️ email gestuurd waarin ik vraag of ze nogmaals kan bellen","stages":[]},{"id":1776890784807,"date":"2026-04-22","platform":"Referral","region":"other","title":"Account manager","company":"Cigna","url":"","type":"Referral","status":"Rejected","notes":"Waiting to hear back. Send email monday","stages":[]},{"id":1776890690433,"date":"2026-04-22","platform":"Recruiter Reached Out","region":"other","title":"Lead generator","company":"","url":"","type":"Recruiter Outreach","status":"Interview","notes":"‼️I need to send my updated CV","stages":[{"id":1776890734679,"stageNum":1,"type":"Video Interview","date":"2026-04-22","status":"Scheduled","notes":""}]}],"outreach":[],"targets":{"LinkedIn Dubai":15,"Naukrigulf":5,"Bayt.com":5,"Dubizzle Jobs":5,"GulfTalent":5,"LinkedIn Netherlands":10,"Indeed Netherlands":10,"WorkInHolland":0,"Glassdoor NL":0,"Expatica NL":0,"Himalayas":5,"Remote.co":5,"LinkedIn Remote":5,"Other Remote":0},"_ts":1776926983563}